{"v":"5.2.1","fr":30,"ip":0,"op":46,"w":85,"h":130,"nm":"EX-view more","ddd":0,"assets":[],"layers":[{"ddd":0,"ind":1,"ty":4,"nm":"看 Outlines","sr":1,"ks":{"o":{"a":0,"k":80,"ix":11},"r":{"a":0,"k":0,"ix":10},"p":{"s":true,"x":{"a":0,"k":13.25,"ix":3},"y":{"a":0,"k":99,"ix":4}},"a":{"a":0,"k":[0,0,0],"ix":1},"s":{"a":0,"k":[100,100,100],"ix":6}},"ao":0,"shapes":[{"ty":"gr","it":[{"ind":0,"ty":"sh","ix":1,"ks":{"a":0,"k":{"i":[[0,0],[0,0],[0,0],[0.387,-0.556],[0,0],[0,0],[0,0],[2.635,-1.789],[0,0],[-1.233,1.112],[0,0],[0,0],[0,0],[0,0],[0,0],[0,0],[0,0],[0,0],[-0.435,0.58],[0,0],[0,0],[0,0],[-0.29,0.58],[0,0],[0,0],[0,0],[-0.218,0.653],[-2.296,0.508],[0,0],[6.864,0],[0,0],[-2.369,0.145],[0.266,-0.58]],"o":[[0,0],[0,0],[-0.314,0.532],[0,0],[0,0],[0,0],[-1.716,2.03],[0,0],[1.499,-1.015],[0,0],[0,0],[0,0],[0,0],[0,0],[0,0],[0,0],[0,0],[0.459,-0.532],[0,0],[0,0],[0,0],[0.314,-0.532],[0,0],[0,0],[0,0],[0.242,-0.604],[3.045,-0.242],[0,0],[-4.52,0.918],[0,0],[2.755,0],[-0.242,0.58],[0,0]],"v":[[-9.051,5.34],[-9.051,6.839],[-2.187,6.839],[-3.25,8.482],[-10.356,8.482],[-10.356,10.029],[-4.459,10.029],[-10.985,15.733],[-10.042,17.232],[-5.958,14.017],[-5.958,23.081],[-4.29,23.081],[-4.29,22.042],[6.635,22.042],[6.635,23.081],[8.303,23.081],[8.303,11.697],[-3.686,11.697],[-2.356,10.029],[10.72,10.029],[10.72,8.482],[-1.293,8.482],[-0.374,6.839],[9.318,6.839],[9.318,5.34],[0.327,5.34],[1.028,3.455],[9.028,2.343],[8.23,0.965],[-8.834,2.343],[-8.326,3.793],[-0.64,3.576],[-1.389,5.34]],"c":true},"ix":2},"nm":"?","mn":"ADBE Vector Shape - Group","hd":false},{"ind":1,"ty":"sh","ix":2,"ks":{"a":0,"k":{"i":[[0,0],[0,0],[0,0],[0,0]],"o":[[0,0],[0,0],[0,0],[0,0]],"v":[[-4.29,16.096],[6.635,16.096],[6.635,17.618],[-4.29,17.618]],"c":true},"ix":2},"nm":"?","mn":"ADBE Vector Shape - Group","hd":false},{"ind":2,"ty":"sh","ix":3,"ks":{"a":0,"k":{"i":[[0,0],[0,0],[0,0],[0,0]],"o":[[0,0],[0,0],[0,0],[0,0]],"v":[[6.635,14.742],[-4.29,14.742],[-4.29,13.123],[6.635,13.123]],"c":true},"ix":2},"nm":"?","mn":"ADBE Vector Shape - Group","hd":false},{"ind":3,"ty":"sh","ix":4,"ks":{"a":0,"k":{"i":[[0,0],[0,0],[0,0],[0,0]],"o":[[0,0],[0,0],[0,0],[0,0]],"v":[[-4.29,18.972],[6.635,18.972],[6.635,20.615],[-4.29,20.615]],"c":true},"ix":2},"nm":"?","mn":"ADBE Vector Shape - Group","hd":false},{"ty":"mm","mm":1,"nm":"Merge Paths 1","mn":"ADBE Vector Filter - Merge","hd":false},{"ty":"st","c":{"a":0,"k":[0,0,0,1],"ix":3},"o":{"a":0,"k":100,"ix":4},"w":{"a":0,"k":0.01,"ix":5},"lc":1,"lj":1,"ml":4,"ml2":{"a":0,"k":4,"ix":8},"nm":"Stroke 1","mn":"ADBE Vector Graphic - Stroke","hd":false},{"ty":"fl","c":{"a":0,"k":[0.6,0.6,0.6,1],"ix":4},"o":{"a":0,"k":100,"ix":5},"r":1,"nm":"Fill 1","mn":"ADBE Vector Graphic - Fill","hd":false},{"ty":"tr","p":{"a":0,"k":[0,0],"ix":2},"a":{"a":0,"k":[0,0],"ix":1},"s":{"a":0,"k":[100,100],"ix":3},"r":{"a":0,"k":0,"ix":6},"o":{"a":0,"k":100,"ix":7},"sk":{"a":0,"k":0,"ix":4},"sa":{"a":0,"k":0,"ix":5},"nm":"Transform"}],"nm":"?","np":7,"cix":2,"ix":1,"mn":"ADBE Vector Group","hd":false}],"ip":35,"op":46,"st":8,"bm":0},{"ddd":0,"ind":2,"ty":4,"nm":"查 Outlines","sr":1,"ks":{"o":{"a":0,"k":80,"ix":11},"r":{"a":0,"k":0,"ix":10},"p":{"s":true,"x":{"a":0,"k":13.25,"ix":3},"y":{"a":0,"k":68.75,"ix":4}},"a":{"a":0,"k":[0,0,0],"ix":1},"s":{"a":0,"k":[100,100,100],"ix":6}},"ao":0,"shapes":[{"ty":"gr","it":[{"ind":0,"ty":"sh","ix":1,"ks":{"a":0,"k":{"i":[[0,0],[0,0],[0,0],[0,0]],"o":[[0,0],[0,0],[0,0],[0,0]],"v":[[-7.094,9.956],[-7.094,18.851],[7.36,18.851],[7.36,9.956]],"c":true},"ix":2},"nm":"?","mn":"ADBE Vector Shape - Group","hd":false},{"ind":1,"ty":"sh","ix":2,"ks":{"a":0,"k":{"i":[[0,0],[0,0],[0,0],[0,0]],"o":[[0,0],[0,0],[0,0],[0,0]],"v":[[5.668,17.304],[-5.402,17.304],[-5.402,15.177],[5.668,15.177]],"c":true},"ix":2},"nm":"?","mn":"ADBE Vector Shape - Group","hd":false},{"ind":2,"ty":"sh","ix":3,"ks":{"a":0,"k":{"i":[[0,0],[0,0],[0,0],[0,0]],"o":[[0,0],[0,0],[0,0],[0,0]],"v":[[-5.402,13.703],[-5.402,11.503],[5.668,11.503],[5.668,13.703]],"c":true},"ix":2},"nm":"?","mn":"ADBE Vector Shape - Group","hd":false},{"ind":3,"ty":"sh","ix":4,"ks":{"a":0,"k":{"i":[[0,0],[0,0],[0,0],[3.867,-1.112],[0,0],[-1.885,2.32],[0,0],[0,0],[0,0],[0,0],[0,0],[-4.351,-1.474],[0,0],[1.813,1.764],[0,0],[0,0],[0,0],[0,0],[0,0],[0,0]],"o":[[0,0],[0,0],[-1.885,1.692],[0,0],[4.23,-1.523],[0,0],[0,0],[0,0],[0,0],[0,0],[1.789,2.369],[0,0],[-3.819,-1.015],[0,0],[0,0],[0,0],[0,0],[0,0],[0,0],[0,0]],"v":[[-9.801,3.068],[-9.801,4.663],[-2.332,4.663],[-10.961,8.893],[-10.042,10.44],[-0.858,4.663],[-0.713,4.663],[-0.713,9.183],[0.979,9.183],[0.979,4.663],[1.124,4.663],[10.333,10.415],[11.082,8.844],[2.647,4.663],[10.067,4.663],[10.067,3.068],[0.979,3.068],[0.979,0.844],[-0.713,0.844],[-0.713,3.068]],"c":true},"ix":2},"nm":"?","mn":"ADBE Vector Shape - Group","hd":false},{"ind":4,"ty":"sh","ix":5,"ks":{"a":0,"k":{"i":[[0,0],[0,0],[0,0],[0,0]],"o":[[0,0],[0,0],[0,0],[0,0]],"v":[[-10.284,20.736],[-10.284,22.355],[10.478,22.355],[10.478,20.736]],"c":true},"ix":2},"nm":"?","mn":"ADBE Vector Shape - Group","hd":false},{"ty":"mm","mm":1,"nm":"Merge Paths 1","mn":"ADBE Vector Filter - Merge","hd":false},{"ty":"st","c":{"a":0,"k":[0,0,0,1],"ix":3},"o":{"a":0,"k":100,"ix":4},"w":{"a":0,"k":0.01,"ix":5},"lc":1,"lj":1,"ml":4,"ml2":{"a":0,"k":4,"ix":8},"nm":"Stroke 1","mn":"ADBE Vector Graphic - Stroke","hd":false},{"ty":"fl","c":{"a":0,"k":[0.6,0.6,0.6,1],"ix":4},"o":{"a":0,"k":100,"ix":5},"r":1,"nm":"Fill 1","mn":"ADBE Vector Graphic - Fill","hd":false},{"ty":"tr","p":{"a":0,"k":[0,0],"ix":2},"a":{"a":0,"k":[0,0],"ix":1},"s":{"a":0,"k":[100,100],"ix":3},"r":{"a":0,"k":0,"ix":6},"o":{"a":0,"k":100,"ix":7},"sk":{"a":0,"k":0,"ix":4},"sa":{"a":0,"k":0,"ix":5},"nm":"Transform"}],"nm":"?","np":8,"cix":2,"ix":1,"mn":"ADBE Vector Group","hd":false}],"ip":35,"op":46,"st":8,"bm":0},{"ddd":0,"ind":3,"ty":4,"nm":"放 Outlines","sr":1,"ks":{"o":{"a":0,"k":80,"ix":11},"r":{"a":0,"k":0,"ix":10},"p":{"s":true,"x":{"a":0,"k":13.25,"ix":3},"y":{"a":0,"k":38.75,"ix":4}},"a":{"a":0,"k":[0,0,0],"ix":1},"s":{"a":0,"k":[100,100,100],"ix":6}},"ao":0,"shapes":[{"ty":"gr","it":[{"ind":0,"ty":"sh","ix":1,"ks":{"a":0,"k":{"i":[[-0.435,0.677],[-1.136,-1.934],[2.32,-1.257],[0,0],[-1.45,1.934],[-2.103,-1.208],[0,0],[1.523,2.175],[-0.145,4.061],[0,0],[0,0],[0,0],[-0.218,1.233],[0,0],[1.885,-2.417],[0,0]],"o":[[0.773,2.49],[-1.402,1.958],[0,0],[2.272,-1.305],[1.499,2.127],[0,0],[-2.079,-1.16],[1.74,-2.876],[0,0],[0,0],[0,0],[0.314,-1.063],[0,0],[-0.677,4.085],[0,0],[0.483,-0.58]],"v":[[1.076,9.981],[3.928,16.603],[-1.631,21.413],[-0.64,22.984],[4.919,18.126],[10.333,23.129],[11.324,21.655],[5.91,16.652],[8.738,6.234],[10.526,6.234],[10.526,4.567],[3.396,4.567],[4.194,1.11],[2.478,0.82],[-1.365,10.585],[-0.302,11.866]],"c":true},"ix":2},"nm":"?","mn":"ADBE Vector Shape - Group","hd":false},{"ind":1,"ty":"sh","ix":2,"ks":{"a":0,"k":{"i":[[-0.242,0.677],[0,0],[1.354,-2.49],[0.725,2.659]],"o":[[0,0],[-0.121,3.384],[-1.136,-1.958],[0.29,-0.604]],"v":[[2.865,6.234],[7.07,6.234],[4.871,15.056],[2.067,8.144]],"c":true},"ix":2},"nm":"?","mn":"ADBE Vector Shape - Group","hd":false},{"ind":2,"ty":"sh","ix":3,"ks":{"a":0,"k":{"i":[[0,0],[0,0],[0,0],[0,0],[1.982,-2.78],[0,0],[-0.338,5.172],[0,0],[0.169,-0.918],[0.87,0],[0.677,0.048],[0,0],[-0.314,0],[-0.242,1.378],[0,5.873],[0,0],[0,0.483],[0,0],[0,0],[0,0],[0,0],[0.677,1.402],[0,0],[-0.435,-1.16]],"o":[[0,0],[0,0],[0,0],[-0.048,6.139],[0,0],[1.789,-2.562],[0,0],[-0.024,4.786],[-0.169,0.798],[-0.532,0],[0,0],[0.798,0.048],[1.716,0],[0.218,-1.354],[0,0],[0,-0.435],[0,0],[0,0],[0,0],[0,0],[-0.387,-1.16],[0,0],[0.58,1.088],[0,0]],"v":[[-10.671,4.542],[-10.671,6.21],[-8.157,6.21],[-8.157,8.434],[-11.178,21.824],[-9.825,23.008],[-6.634,11.407],[-3.589,11.407],[-3.879,19.987],[-5.45,21.196],[-7.263,21.123],[-6.876,22.622],[-5.208,22.718],[-2.284,20.64],[-1.945,9.812],[-6.562,9.812],[-6.538,8.434],[-6.538,6.21],[-0.664,6.21],[-0.664,4.542],[-4.29,4.542],[-5.909,0.699],[-7.601,1.183],[-6.054,4.542]],"c":true},"ix":2},"nm":"?","mn":"ADBE Vector Shape - Group","hd":false},{"ty":"mm","mm":1,"nm":"Merge Paths 1","mn":"ADBE Vector Filter - Merge","hd":false},{"ty":"st","c":{"a":0,"k":[0,0,0,1],"ix":3},"o":{"a":0,"k":100,"ix":4},"w":{"a":0,"k":0.01,"ix":5},"lc":1,"lj":1,"ml":4,"ml2":{"a":0,"k":4,"ix":8},"nm":"Stroke 1","mn":"ADBE Vector Graphic - Stroke","hd":false},{"ty":"fl","c":{"a":0,"k":[0.6,0.6,0.6,1],"ix":4},"o":{"a":0,"k":100,"ix":5},"r":1,"nm":"Fill 1","mn":"ADBE Vector Graphic - Fill","hd":false},{"ty":"tr","p":{"a":0,"k":[0,0],"ix":2},"a":{"a":0,"k":[0,0],"ix":1},"s":{"a":0,"k":[100,100],"ix":3},"r":{"a":0,"k":0,"ix":6},"o":{"a":0,"k":100,"ix":7},"sk":{"a":0,"k":0,"ix":4},"sa":{"a":0,"k":0,"ix":5},"nm":"Transform"}],"nm":"?","np":6,"cix":2,"ix":1,"mn":"ADBE Vector Group","hd":false}],"ip":35,"op":46,"st":8,"bm":0},{"ddd":0,"ind":4,"ty":4,"nm":"释 Outlines","sr":1,"ks":{"o":{"a":0,"k":80,"ix":11},"r":{"a":0,"k":0,"ix":10},"p":{"s":true,"x":{"a":0,"k":13.25,"ix":3},"y":{"a":0,"k":8.25,"ix":4}},"a":{"a":0,"k":[0,0,0],"ix":1},"s":{"a":0,"k":[100,100,100],"ix":6}},"ao":0,"shapes":[{"ty":"gr","it":[{"ind":0,"ty":"sh","ix":1,"ks":{"a":0,"k":{"i":[[0,0],[0,0],[0,0],[1.982,-1.958],[0,0],[-0.967,2.079],[0,0],[0,0],[0,0],[-1.015,-1.354],[0,0],[1.16,1.015],[0,0],[0,0],[0,0],[0,0],[0,0],[-1.112,0.29],[0,0],[3.335,-0.29],[0,0],[-1.257,0.193],[0,0]],"o":[[0,0],[0,0],[-0.87,2.465],[0,0],[1.571,-1.692],[0,0],[0,0],[0,0],[0.725,0.822],[0,0],[-1.208,-1.305],[0,0],[0,0],[0,0],[0,0],[0,0],[1.257,-0.242],[0,0],[-2.562,0.725],[0,0],[1.354,-0.145],[0,0],[0,0]],"v":[[-10.646,9.812],[-10.646,11.455],[-6.779,11.455],[-11.082,18.102],[-10.405,19.866],[-6.61,14.235],[-6.61,23.057],[-4.918,23.057],[-4.918,14.38],[-2.332,17.643],[-1.341,16.144],[-4.918,12.664],[-4.918,11.455],[-1.486,11.455],[-1.486,9.812],[-4.918,9.812],[-4.918,3.189],[-1.365,2.367],[-1.921,0.893],[-10.792,2.416],[-10.501,3.987],[-6.61,3.479],[-6.61,9.812]],"c":true},"ix":2},"nm":"?","mn":"ADBE Vector Shape - Group","hd":false},{"ind":1,"ty":"sh","ix":2,"ks":{"a":0,"k":{"i":[[0,0],[0,0],[0,0],[0,0],[0,0],[0,0],[0,0],[0,0],[0,0],[0,0],[0,0],[0,0],[0,0],[0,0],[0,0],[0,0],[0,0],[0,0],[0,0],[0,0]],"o":[[0,0],[0,0],[0,0],[0,0],[0,0],[0,0],[0,0],[0,0],[0,0],[0,0],[0,0],[0,0],[0,0],[0,0],[0,0],[0,0],[0,0],[0,0],[0,0],[0,0]],"v":[[-1.027,17.232],[-1.027,18.875],[4.194,18.875],[4.194,23.032],[5.934,23.032],[5.934,18.875],[11.01,18.875],[11.01,17.232],[5.934,17.232],[5.934,14.573],[10.333,14.573],[10.333,12.978],[5.934,12.978],[5.934,10.609],[4.194,10.609],[4.194,12.978],[-0.181,12.978],[-0.181,14.573],[4.194,14.573],[4.194,17.232]],"c":true},"ix":2},"nm":"?","mn":"ADBE Vector Shape - Group","hd":false},{"ind":2,"ty":"sh","ix":3,"ks":{"a":0,"k":{"i":[[0,0],[0.532,-1.136],[0,0],[-0.387,1.668]],"o":[[-0.387,1.716],[0,0],[0.58,-1.257],[0,0]],"v":[[-2.767,4.18],[-4.121,8.458],[-2.719,8.966],[-1.293,4.567]],"c":true},"ix":2},"nm":"?","mn":"ADBE Vector Shape - Group","hd":false},{"ind":3,"ty":"sh","ix":4,"ks":{"a":0,"k":{"i":[[0.58,1.16],[0,0],[-0.483,-1.474],[0,0]],"o":[[0,0],[0.604,1.112],[0,0],[-0.435,-1.354]],"v":[[-9.1,4.639],[-10.55,5.123],[-8.906,9.014],[-7.577,8.41]],"c":true},"ix":2},"nm":"?","mn":"ADBE Vector Shape - Group","hd":false},{"ind":4,"ty":"sh","ix":5,"ks":{"a":0,"k":{"i":[[0,0],[-1.571,-1.281],[1.813,-0.483],[0,0],[-1.499,0.894],[-2.03,-0.628],[0,0],[1.257,0.628],[-0.604,1.837],[0,0],[0,0],[0,0]],"o":[[0.508,1.74],[-1.305,0.725],[0,0],[2.079,-0.58],[1.402,0.87],[0,0],[-1.74,-0.532],[1.595,-1.305],[0,0],[0,0],[0,0],[0,0]],"v":[[0.472,3.431],[3.59,7.95],[-1.099,9.739],[-0.253,11.213],[5.112,9.014],[10.26,11.238],[11.058,9.739],[6.587,7.999],[9.874,3.31],[9.874,1.86],[-0.543,1.86],[-0.543,3.431]],"c":true},"ix":2},"nm":"?","mn":"ADBE Vector Shape - Group","hd":false},{"ind":5,"ty":"sh","ix":6,"ks":{"a":0,"k":{"i":[[1.426,-1.039],[0.387,1.378],[0,0]],"o":[[-1.547,-1.039],[0,0],[-0.628,1.378]],"v":[[5.016,7.056],[2.139,3.431],[8.109,3.431]],"c":true},"ix":2},"nm":"?","mn":"ADBE Vector Shape - Group","hd":false},{"ty":"mm","mm":1,"nm":"Merge Paths 1","mn":"ADBE Vector Filter - Merge","hd":false},{"ty":"st","c":{"a":0,"k":[0,0,0,1],"ix":3},"o":{"a":0,"k":100,"ix":4},"w":{"a":0,"k":0.01,"ix":5},"lc":1,"lj":1,"ml":4,"ml2":{"a":0,"k":4,"ix":8},"nm":"Stroke 1","mn":"ADBE Vector Graphic - Stroke","hd":false},{"ty":"fl","c":{"a":0,"k":[0.6,0.6,0.6,1],"ix":4},"o":{"a":0,"k":100,"ix":5},"r":1,"nm":"Fill 1","mn":"ADBE Vector Graphic - Fill","hd":false},{"ty":"tr","p":{"a":0,"k":[0,0],"ix":2},"a":{"a":0,"k":[0,0],"ix":1},"s":{"a":0,"k":[100,100],"ix":3},"r":{"a":0,"k":0,"ix":6},"o":{"a":0,"k":100,"ix":7},"sk":{"a":0,"k":0,"ix":4},"sa":{"a":0,"k":0,"ix":5},"nm":"Transform"}],"nm":"?","np":9,"cix":2,"ix":1,"mn":"ADBE Vector Group","hd":false}],"ip":35,"op":46,"st":8,"bm":0},{"ddd":0,"ind":5,"ty":4,"nm":"多 Outlines","sr":1,"ks":{"o":{"a":0,"k":80,"ix":11},"r":{"a":0,"k":0,"ix":10},"p":{"s":true,"x":{"a":1,"k":[{"i":{"x":[0.833],"y":[0.833]},"o":{"x":[0.167],"y":[0.167]},"n":["0p833_0p833_0p167_0p167"],"t":0,"s":[68.375],"e":[13.25]},{"t":30}],"ix":3},"y":{"a":0,"k":99,"ix":4}},"a":{"a":0,"k":[0,0,0],"ix":1},"s":{"a":0,"k":[100,100,100],"ix":6}},"ao":0,"shapes":[{"ty":"gr","it":[{"ind":0,"ty":"sh","ix":1,"ks":{"a":0,"k":{"i":[[0,0],[4.302,-0.822],[0,0],[-1.885,1.112],[0,0],[2.514,-1.015],[0.87,0.822],[0,0],[-0.749,-0.918],[2.175,-0.145],[0,0],[-2.61,4.641],[0,0],[0,0],[-0.435,0.483]],"o":[[-2.127,2.32],[0,0],[2.586,-0.58],[0,0],[-1.354,1.982],[-0.773,-0.967],[0,0],[0.822,0.749],[-1.74,0.508],[0,0],[7.058,-0.556],[0,0],[0,0],[0.483,-0.435],[0,0]],"v":[[-0.012,0.82],[-9.656,5.509],[-8.64,7.104],[-1.945,4.567],[5.112,4.567],[-0.713,9.086],[-3.178,6.428],[-4.701,7.153],[-2.332,9.667],[-8.181,10.633],[-7.432,12.204],[7.094,4.397],[7.094,3.02],[0.157,3.02],[1.535,1.642]],"c":true},"ix":2},"nm":"?","mn":"ADBE Vector Shape - Group","hd":false},{"ind":1,"ty":"sh","ix":2,"ks":{"a":0,"k":{"i":[[0.918,0.943],[0,0],[-0.822,-1.088],[3.771,-0.024],[0,0],[-3.432,5.704],[0,0],[0,0],[-0.58,0.58],[0,0],[5.269,-0.532],[0,0],[-2.127,1.015],[0,0],[2.683,-1.16]],"o":[[0,0],[0.894,0.87],[-2.731,0.918],[0,0],[9.378,-0.218],[0,0],[0,0],[0.677,-0.508],[0,0],[-2.514,2.659],[0,0],[2.925,-0.508],[0,0],[-1.547,2.127],[-0.822,-1.088]],"v":[[-0.93,15.927],[-2.477,16.652],[0.085,19.6],[-9.68,21.002],[-8.979,22.67],[10.212,13.8],[10.212,12.422],[3.59,12.422],[5.451,10.778],[3.952,9.957],[-7.722,14.766],[-6.683,16.313],[0.883,14.017],[8.037,14.017],[1.704,18.972]],"c":true},"ix":2},"nm":"?","mn":"ADBE Vector Shape - Group","hd":false},{"ty":"mm","mm":1,"nm":"Merge Paths 1","mn":"ADBE Vector Filter - Merge","hd":false},{"ty":"st","c":{"a":0,"k":[0,0,0,1],"ix":3},"o":{"a":0,"k":100,"ix":4},"w":{"a":0,"k":0.01,"ix":5},"lc":1,"lj":1,"ml":4,"ml2":{"a":0,"k":4,"ix":8},"nm":"Stroke 1","mn":"ADBE Vector Graphic - Stroke","hd":false},{"ty":"fl","c":{"a":0,"k":[0.6,0.6,0.6,1],"ix":4},"o":{"a":0,"k":100,"ix":5},"r":1,"nm":"Fill 1","mn":"ADBE Vector Graphic - Fill","hd":false},{"ty":"tr","p":{"a":0,"k":[0,0],"ix":2},"a":{"a":0,"k":[0,0],"ix":1},"s":{"a":0,"k":[100,100],"ix":3},"r":{"a":0,"k":0,"ix":6},"o":{"a":0,"k":100,"ix":7},"sk":{"a":0,"k":0,"ix":4},"sa":{"a":0,"k":0,"ix":5},"nm":"Transform"}],"nm":"?","np":5,"cix":2,"ix":1,"mn":"ADBE Vector Group","hd":false}],"ip":0,"op":35,"st":-7,"bm":0},{"ddd":0,"ind":6,"ty":4,"nm":"更 Outlines","sr":1,"ks":{"o":{"a":0,"k":80,"ix":11},"r":{"a":0,"k":0,"ix":10},"p":{"s":true,"x":{"a":1,"k":[{"i":{"x":[0.833],"y":[0.833]},"o":{"x":[0.167],"y":[0.167]},"n":["0p833_0p833_0p167_0p167"],"t":0,"s":[51.313],"e":[13.25]},{"t":30}],"ix":3},"y":{"a":0,"k":68.75,"ix":4}},"a":{"a":0,"k":[0,0,0],"ix":1},"s":{"a":0,"k":[100,100,100],"ix":6}},"ao":0,"shapes":[{"ty":"gr","it":[{"ind":0,"ty":"sh","ix":1,"ks":{"a":0,"k":{"i":[[0,0],[0,0],[0,0],[0,0],[0,0],[0,0],[0,0],[0.58,-0.822],[1.136,0.943],[0,0],[-1.402,-0.773],[3.36,-0.266],[0,0],[-1.692,1.45],[-4.858,-0.193],[0,0],[3.384,1.426],[-0.29,1.595],[0,0],[0,0],[0,0],[0,0],[0,0],[0,0]],"o":[[0,0],[0,0],[0,0],[0,0],[0,0],[0,0],[-0.242,1.257],[-1.354,-0.701],[0,0],[1.184,1.015],[-1.547,1.112],[0,0],[3.843,-0.435],[3.601,1.644],[0,0],[-4.641,-0.145],[0.677,-0.967],[0,0],[0,0],[0,0],[0,0],[0,0],[0,0],[0,0]],"v":[[-10.26,1.86],[-10.26,3.479],[-0.785,3.479],[-0.785,5.582],[-8.181,5.582],[-8.181,15.153],[-1.099,15.153],[-2.356,18.271],[-6.103,15.806],[-7.432,16.724],[-3.541,19.407],[-10.912,21.461],[-10.163,23.057],[-1.849,20.253],[10.841,23.032],[11.276,21.365],[-0.761,18.996],[0.665,15.153],[8.448,15.153],[8.448,5.582],[0.955,5.582],[0.955,3.479],[10.454,3.479],[10.454,1.86]],"c":true},"ix":2},"nm":"?","mn":"ADBE Vector Shape - Group","hd":false},{"ind":1,"ty":"sh","ix":2,"ks":{"a":0,"k":{"i":[[0,0],[0,0],[0,0],[0,0],[0,0]],"o":[[0,0],[0,0],[0,0],[0,0],[0,0]],"v":[[6.732,13.63],[0.883,13.63],[0.955,11.914],[0.955,11.068],[6.732,11.068]],"c":true},"ix":2},"nm":"?","mn":"ADBE Vector Shape - Group","hd":false},{"ind":2,"ty":"sh","ix":3,"ks":{"a":0,"k":{"i":[[0.048,-0.556],[0,0],[0,0],[0,0],[0,0]],"o":[[0,0],[0,0],[0,0],[0,0],[0,0.58]],"v":[[-0.858,13.63],[-6.465,13.63],[-6.465,11.068],[-0.785,11.068],[-0.785,11.914]],"c":true},"ix":2},"nm":"?","mn":"ADBE Vector Shape - Group","hd":false},{"ind":3,"ty":"sh","ix":4,"ks":{"a":0,"k":{"i":[[0,0],[0,0],[0,0],[0,0]],"o":[[0,0],[0,0],[0,0],[0,0]],"v":[[-6.465,9.618],[-6.465,7.08],[-0.785,7.08],[-0.785,9.618]],"c":true},"ix":2},"nm":"?","mn":"ADBE Vector Shape - Group","hd":false},{"ind":4,"ty":"sh","ix":5,"ks":{"a":0,"k":{"i":[[0,0],[0,0],[0,0],[0,0]],"o":[[0,0],[0,0],[0,0],[0,0]],"v":[[0.955,7.08],[6.732,7.08],[6.732,9.618],[0.955,9.618]],"c":true},"ix":2},"nm":"?","mn":"ADBE Vector Shape - Group","hd":false},{"ty":"mm","mm":1,"nm":"Merge Paths 1","mn":"ADBE Vector Filter - Merge","hd":false},{"ty":"st","c":{"a":0,"k":[0,0,0,1],"ix":3},"o":{"a":0,"k":100,"ix":4},"w":{"a":0,"k":0.01,"ix":5},"lc":1,"lj":1,"ml":4,"ml2":{"a":0,"k":4,"ix":8},"nm":"Stroke 1","mn":"ADBE Vector Graphic - Stroke","hd":false},{"ty":"fl","c":{"a":0,"k":[0.6,0.6,0.6,1],"ix":4},"o":{"a":0,"k":100,"ix":5},"r":1,"nm":"Fill 1","mn":"ADBE Vector Graphic - Fill","hd":false},{"ty":"tr","p":{"a":0,"k":[0,0],"ix":2},"a":{"a":0,"k":[0,0],"ix":1},"s":{"a":0,"k":[100,100],"ix":3},"r":{"a":0,"k":0,"ix":6},"o":{"a":0,"k":100,"ix":7},"sk":{"a":0,"k":0,"ix":4},"sa":{"a":0,"k":0,"ix":5},"nm":"Transform"}],"nm":"?","np":8,"cix":2,"ix":1,"mn":"ADBE Vector Group","hd":false}],"ip":0,"op":35,"st":-7,"bm":0},{"ddd":0,"ind":7,"ty":4,"nm":"看 Outlines","sr":1,"ks":{"o":{"a":0,"k":80,"ix":11},"r":{"a":0,"k":0,"ix":10},"p":{"s":true,"x":{"a":1,"k":[{"i":{"x":[0.833],"y":[0.833]},"o":{"x":[0.167],"y":[0.167]},"n":["0p833_0p833_0p167_0p167"],"t":0,"s":[33.03],"e":[13.25]},{"t":30}],"ix":3},"y":{"a":0,"k":38.75,"ix":4}},"a":{"a":0,"k":[0,0,0],"ix":1},"s":{"a":0,"k":[100,100,100],"ix":6}},"ao":0,"shapes":[{"ty":"gr","it":[{"ind":0,"ty":"sh","ix":1,"ks":{"a":0,"k":{"i":[[0,0],[0,0],[0,0],[0.387,-0.556],[0,0],[0,0],[0,0],[2.635,-1.789],[0,0],[-1.233,1.112],[0,0],[0,0],[0,0],[0,0],[0,0],[0,0],[0,0],[0,0],[-0.435,0.58],[0,0],[0,0],[0,0],[-0.29,0.58],[0,0],[0,0],[0,0],[-0.218,0.653],[-2.296,0.508],[0,0],[6.864,0],[0,0],[-2.369,0.145],[0.266,-0.58]],"o":[[0,0],[0,0],[-0.314,0.532],[0,0],[0,0],[0,0],[-1.716,2.03],[0,0],[1.499,-1.015],[0,0],[0,0],[0,0],[0,0],[0,0],[0,0],[0,0],[0,0],[0.459,-0.532],[0,0],[0,0],[0,0],[0.314,-0.532],[0,0],[0,0],[0,0],[0.242,-0.604],[3.045,-0.242],[0,0],[-4.52,0.918],[0,0],[2.755,0],[-0.242,0.58],[0,0]],"v":[[-9.051,5.34],[-9.051,6.839],[-2.187,6.839],[-3.25,8.482],[-10.356,8.482],[-10.356,10.029],[-4.459,10.029],[-10.985,15.733],[-10.042,17.232],[-5.958,14.017],[-5.958,23.081],[-4.29,23.081],[-4.29,22.042],[6.635,22.042],[6.635,23.081],[8.303,23.081],[8.303,11.697],[-3.686,11.697],[-2.356,10.029],[10.72,10.029],[10.72,8.482],[-1.293,8.482],[-0.374,6.839],[9.318,6.839],[9.318,5.34],[0.327,5.34],[1.028,3.455],[9.028,2.343],[8.23,0.965],[-8.834,2.343],[-8.326,3.793],[-0.64,3.576],[-1.389,5.34]],"c":true},"ix":2},"nm":"?","mn":"ADBE Vector Shape - Group","hd":false},{"ind":1,"ty":"sh","ix":2,"ks":{"a":0,"k":{"i":[[0,0],[0,0],[0,0],[0,0]],"o":[[0,0],[0,0],[0,0],[0,0]],"v":[[-4.29,16.096],[6.635,16.096],[6.635,17.618],[-4.29,17.618]],"c":true},"ix":2},"nm":"?","mn":"ADBE Vector Shape - Group","hd":false},{"ind":2,"ty":"sh","ix":3,"ks":{"a":0,"k":{"i":[[0,0],[0,0],[0,0],[0,0]],"o":[[0,0],[0,0],[0,0],[0,0]],"v":[[6.635,14.742],[-4.29,14.742],[-4.29,13.123],[6.635,13.123]],"c":true},"ix":2},"nm":"?","mn":"ADBE Vector Shape - Group","hd":false},{"ind":3,"ty":"sh","ix":4,"ks":{"a":0,"k":{"i":[[0,0],[0,0],[0,0],[0,0]],"o":[[0,0],[0,0],[0,0],[0,0]],"v":[[-4.29,18.972],[6.635,18.972],[6.635,20.615],[-4.29,20.615]],"c":true},"ix":2},"nm":"?","mn":"ADBE Vector Shape - Group","hd":false},{"ty":"mm","mm":1,"nm":"Merge Paths 1","mn":"ADBE Vector Filter - Merge","hd":false},{"ty":"st","c":{"a":0,"k":[0,0,0,1],"ix":3},"o":{"a":0,"k":100,"ix":4},"w":{"a":0,"k":0.01,"ix":5},"lc":1,"lj":1,"ml":4,"ml2":{"a":0,"k":4,"ix":8},"nm":"Stroke 1","mn":"ADBE Vector Graphic - Stroke","hd":false},{"ty":"fl","c":{"a":0,"k":[0.6,0.6,0.6,1],"ix":4},"o":{"a":0,"k":100,"ix":5},"r":1,"nm":"Fill 1","mn":"ADBE Vector Graphic - Fill","hd":false},{"ty":"tr","p":{"a":0,"k":[0,0],"ix":2},"a":{"a":0,"k":[0,0],"ix":1},"s":{"a":0,"k":[100,100],"ix":3},"r":{"a":0,"k":0,"ix":6},"o":{"a":0,"k":100,"ix":7},"sk":{"a":0,"k":0,"ix":4},"sa":{"a":0,"k":0,"ix":5},"nm":"Transform"}],"nm":"?","np":7,"cix":2,"ix":1,"mn":"ADBE Vector Group","hd":false}],"ip":0,"op":35,"st":-7,"bm":0},{"ddd":0,"ind":8,"ty":4,"nm":"查 Outlines","sr":1,"ks":{"o":{"a":0,"k":80,"ix":11},"r":{"a":0,"k":0,"ix":10},"p":{"s":true,"x":{"a":0,"k":14.689,"ix":3},"y":{"a":0,"k":8.25,"ix":4}},"a":{"a":0,"k":[0,0,0],"ix":1},"s":{"a":0,"k":[100,100,100],"ix":6}},"ao":0,"shapes":[{"ty":"gr","it":[{"ind":0,"ty":"sh","ix":1,"ks":{"a":0,"k":{"i":[[0,0],[0,0],[0,0],[0,0]],"o":[[0,0],[0,0],[0,0],[0,0]],"v":[[-7.094,9.956],[-7.094,18.851],[7.36,18.851],[7.36,9.956]],"c":true},"ix":2},"nm":"?","mn":"ADBE Vector Shape - Group","hd":false},{"ind":1,"ty":"sh","ix":2,"ks":{"a":0,"k":{"i":[[0,0],[0,0],[0,0],[0,0]],"o":[[0,0],[0,0],[0,0],[0,0]],"v":[[5.668,17.304],[-5.402,17.304],[-5.402,15.177],[5.668,15.177]],"c":true},"ix":2},"nm":"?","mn":"ADBE Vector Shape - Group","hd":false},{"ind":2,"ty":"sh","ix":3,"ks":{"a":0,"k":{"i":[[0,0],[0,0],[0,0],[0,0]],"o":[[0,0],[0,0],[0,0],[0,0]],"v":[[-5.402,13.703],[-5.402,11.503],[5.668,11.503],[5.668,13.703]],"c":true},"ix":2},"nm":"?","mn":"ADBE Vector Shape - Group","hd":false},{"ind":3,"ty":"sh","ix":4,"ks":{"a":0,"k":{"i":[[0,0],[0,0],[0,0],[3.867,-1.112],[0,0],[-1.885,2.32],[0,0],[0,0],[0,0],[0,0],[0,0],[-4.351,-1.474],[0,0],[1.813,1.764],[0,0],[0,0],[0,0],[0,0],[0,0],[0,0]],"o":[[0,0],[0,0],[-1.885,1.692],[0,0],[4.23,-1.523],[0,0],[0,0],[0,0],[0,0],[0,0],[1.789,2.369],[0,0],[-3.819,-1.015],[0,0],[0,0],[0,0],[0,0],[0,0],[0,0],[0,0]],"v":[[-9.801,3.068],[-9.801,4.663],[-2.332,4.663],[-10.961,8.893],[-10.042,10.44],[-0.858,4.663],[-0.713,4.663],[-0.713,9.183],[0.979,9.183],[0.979,4.663],[1.124,4.663],[10.333,10.415],[11.082,8.844],[2.647,4.663],[10.067,4.663],[10.067,3.068],[0.979,3.068],[0.979,0.844],[-0.713,0.844],[-0.713,3.068]],"c":true},"ix":2},"nm":"?","mn":"ADBE Vector Shape - Group","hd":false},{"ind":4,"ty":"sh","ix":5,"ks":{"a":0,"k":{"i":[[0,0],[0,0],[0,0],[0,0]],"o":[[0,0],[0,0],[0,0],[0,0]],"v":[[-10.284,20.736],[-10.284,22.355],[10.478,22.355],[10.478,20.736]],"c":true},"ix":2},"nm":"?","mn":"ADBE Vector Shape - Group","hd":false},{"ty":"mm","mm":1,"nm":"Merge Paths 1","mn":"ADBE Vector Filter - Merge","hd":false},{"ty":"st","c":{"a":0,"k":[0,0,0,1],"ix":3},"o":{"a":0,"k":100,"ix":4},"w":{"a":0,"k":0.01,"ix":5},"lc":1,"lj":1,"ml":4,"ml2":{"a":0,"k":4,"ix":8},"nm":"Stroke 1","mn":"ADBE Vector Graphic - Stroke","hd":false},{"ty":"fl","c":{"a":0,"k":[0.6,0.6,0.6,1],"ix":4},"o":{"a":0,"k":100,"ix":5},"r":1,"nm":"Fill 1","mn":"ADBE Vector Graphic - Fill","hd":false},{"ty":"tr","p":{"a":0,"k":[0,0],"ix":2},"a":{"a":0,"k":[0,0],"ix":1},"s":{"a":0,"k":[100,100],"ix":3},"r":{"a":0,"k":0,"ix":6},"o":{"a":0,"k":100,"ix":7},"sk":{"a":0,"k":0,"ix":4},"sa":{"a":0,"k":0,"ix":5},"nm":"Transform"}],"nm":"?","np":8,"cix":2,"ix":1,"mn":"ADBE Vector Group","hd":false}],"ip":0,"op":35,"st":-7,"bm":0}],"markers":[]}